{"cameraMode":{"drawMode":0,"name":"Shaded","section":"Shading Mode"},"sceneLighting":true,"audioPlay":false,"sceneViewState":{"showFog":true,"showMaterialUpdate":false,"showSkybox":true,"showFlares":true,"showImageEffects":true,"showParticleSystems":true},"in2DMode":false,"pivot":{"x":24.207073211669923,"y":13.301692962646485,"z":4.672286033630371},"rotation":{"x":-0.21115657687187196,"y":0.772830069065094,"z":-0.32447561621665957,"w":-0.5028963088989258},"size":5.857884883880615,"orthographic":false}